mcp_server.py
bd_jojo_remote_build_mcp-0.1.0.dist-info/METADATA
bd_jojo_remote_build_mcp-0.1.0.dist-info/WHEEL
bd_jojo_remote_build_mcp-0.1.0.dist-info/entry_points.txt
bd_jojo_remote_build_mcp-0.1.0.dist-info/top_level.txt
bd_jojo_remote_build_mcp-0.1.0.dist-info/RECORD
