Metadata-Version: 2.4
Name: bd-jojo-remote-build-mcp
Version: 0.1.0
Summary: MCP Server for JoJo Remote Build in BD
Requires-Python: >=3.10
Requires-Dist: mcp>=1.0.0
